npt_promote/__init__.py
npt_promote/mypy_plugin.py
npt_promote-0.2.dist-info/LICENSE
npt_promote-0.2.dist-info/METADATA
npt_promote-0.2.dist-info/WHEEL
npt_promote-0.2.dist-info/top_level.txt
npt_promote-0.2.dist-info/RECORD
