Metadata-Version: 2.1
Name: npt-promote
Version: 0.2
Summary: Mypy plugin to add type promotions between NumPy and builtin data types.
License: MIT
Project-URL: Homepage, https://github.com/pyvista/npt-promote
Keywords: mypy,typing,numpy
Classifier: Intended Audience :: Science/Research
Classifier: Topic :: Scientific/Engineering :: Information Analysis
Classifier: License :: OSI Approved :: MIT License
Classifier: Operating System :: Microsoft :: Windows
Classifier: Operating System :: POSIX
Classifier: Operating System :: MacOS
Classifier: Programming Language :: Python :: 3.8
Classifier: Programming Language :: Python :: 3.9
Classifier: Programming Language :: Python :: 3.10
Classifier: Programming Language :: Python :: 3.11
Classifier: Programming Language :: Python :: 3.12
Requires-Python: >=3.8
License-File: LICENSE
Requires-Dist: mypy
Requires-Dist: numpy>=1.21
Provides-Extra: dev
Requires-Dist: pytest; extra == "dev"
Requires-Dist: pytest-mypy-plugins; extra == "dev"
Requires-Dist: pre-commit; extra == "dev"
